test/__init__.py
test/test_action.py
test/test_action_meta.py
test/test_add_liquidity_metadata.py
test/test_affiliate_history.py
test/test_affiliate_history_intervals.py
test/test_affiliate_history_item.py
test/test_affiliate_history_meta.py
test/test_balance.py
test/test_block_rewards.py
test/test_bond_metadata.py
test/test_bond_metrics.py
test/test_borrower_details.py
test/test_borrower_pool.py
test/test_borrowers.py
test/test_churn_item.py
test/test_churns.py
test/test_coin.py
test/test_coins.py
test/test_contract_metadata.py
test/test_default_api.py
test/test_depth_history.py
test/test_depth_history_intervals.py
test/test_depth_history_item.py
test/test_depth_history_item_pool.py
test/test_depth_history_meta.py
test/test_earnings_history.py
test/test_earnings_history_intervals.py
test/test_earnings_history_item.py
test/test_earnings_history_item_pool.py
test/test_failed_metadata.py
test/test_genesis_inf.py
test/test_health.py
test/test_height_ts.py
test/test_inline_response200.py
test/test_item_thorname.py
test/test_known_pools.py
test/test_liquidity_history.py
test/test_liquidity_history_intervals.py
test/test_liquidity_history_item.py
test/test_member_details.py
test/test_member_pool.py
test/test_members.py
test/test_metadata.py
test/test_network.py
test/test_network_fees.py
test/test_node.py
test/test_nodes.py
test/test_pool_detail.py
test/test_pool_details.py
test/test_pool_stats_detail.py
test/test_refund_metadata.py
test/test_reserve_history.py
test/test_reserve_intervals.py
test/test_reserve_item.py
test/test_reserve_meta.py
test/test_reverse_thor_names.py
test/test_rune_pool_deposit_metadata.py
test/test_rune_pool_details.py
test/test_rune_pool_history.py
test/test_rune_pool_history_intervals.py
test/test_rune_pool_history_item.py
test/test_rune_pool_history_meta.py
test/test_rune_pool_provider.py
test/test_rune_pool_withdraw_metadata.py
test/test_rune_price_history.py
test/test_rune_price_intervals.py
test/test_rune_price_item.py
xchainpy2_midgard-2.31.0.dist-info/licenses/LICENSE
xchainpy2_midgard-2.31.0.dist-info/METADATA
xchainpy2_midgard-2.31.0.dist-info/WHEEL
xchainpy2_midgard-2.31.0.dist-info/top_level.txt
xchainpy2_midgard-2.31.0.dist-info/RECORD
